zkdumpreader/__init__.py
zkdumpreader/zkdumpreader.py
zkdumpreader-0.0.7.dist-info/LICENCE.txt
zkdumpreader-0.0.7.dist-info/METADATA
zkdumpreader-0.0.7.dist-info/WHEEL
zkdumpreader-0.0.7.dist-info/top_level.txt
zkdumpreader-0.0.7.dist-info/RECORD
